uhlibs/VERSION
uhlibs/__init__.py
uhlibs/azure/__init__.py
uhlibs/azure/keyvault.py
uhlibs/civis/__init__.py
uhlibs/civis/api.py
uhlibs/cli/__init__.py
uhlibs/cli/prompt.py
uhlibs/config.py
uhlibs/db/__init__.py
uhlibs/db/sqlserver.py
uhlibs/flask/__init__.py
uhlibs/flask/app.py
uhlibs/flask/decorators.py
uhlibs/flask/log.py
uhlibs/logging.py
uhlibs/odata/__init__.py
uhlibs/odata/client.py
uhlibs/odata/query.py
uhlibs/sepuede/__init__.py
uhlibs/sepuede/api.py
uhlibs/sepuede/odata.py
uhlibs/strike/__init__.py
uhlibs/strike/sync.py
uhlibs/testing/__init__.py
uhlibs/testing/base.py
uhlibs/testing/contexts.py
uhlibs/testing/fixtures.py
uhlibs/utils/__init__.py
uhlibs/utils/datagenerator.py
uhlibs-0.8.5.dist-info/METADATA
uhlibs-0.8.5.dist-info/WHEEL
uhlibs-0.8.5.dist-info/RECORD
