Metadata-Version: 2.1
Name: uhlibs
Version: 0.8.5
Summary: UHIU Python libraries & utilities
License: Proprietary
Author: Derek Davie
Author-email: ddavie@unitehere.org
Requires-Python: >=3.10,<4.0
Classifier: License :: Other/Proprietary License
Classifier: Operating System :: OS Independent
Classifier: Programming Language :: Python :: 3
Classifier: Programming Language :: Python :: 3.10
Classifier: Programming Language :: Python :: 3.11
Classifier: Programming Language :: Python :: 3.12
Classifier: Programming Language :: Python :: 3.13
Requires-Dist: PyYAML (>=6.0.2,<7.0.0)
Requires-Dist: azure-identity (>=1.19.0,<2.0.0)
Requires-Dist: azure-keyvault-secrets (>=4.9.0,<5.0.0)
Requires-Dist: civis (>=2.3.0,<3.0.0)
Requires-Dist: exceptiongroup (>=1.2.2,<2.0.0)
Requires-Dist: flask
Requires-Dist: prettytable (>=3.11.0,<4.0.0)
Requires-Dist: psycopg
Requires-Dist: pymongo
Requires-Dist: pyodbc
Requires-Dist: python-odata
Requires-Dist: redit
Requires-Dist: reportLab
Requires-Dist: requests (>2)
Requires-Dist: tomli (>=2.0.2,<3.0.0) ; python_version < "3.11"
